krateng/__pkginfo__.py
krateng-1.0.1.dist-info/METADATA
krateng-1.0.1.dist-info/WHEEL
krateng-1.0.1.dist-info/entry_points.txt
krateng-1.0.1.dist-info/top_level.txt
krateng-1.0.1.dist-info/RECORD
